tokenization_layer/__init__.py
tokenization_layer/general.py
tokenization_layer/layers.py
tokenization_layer/pattern_initializers.py
tokenization_layer/util_functions.py
tokenization_layer-0.0.2.dist-info/LICENSE
tokenization_layer-0.0.2.dist-info/METADATA
tokenization_layer-0.0.2.dist-info/WHEEL
tokenization_layer-0.0.2.dist-info/top_level.txt
tokenization_layer-0.0.2.dist-info/RECORD
