Metadata-Version: 2.1
Name: tokenization-layer
Version: 0.0.2
Summary: An NLP tokenization algorithm that is a trainable layer for neural networks.
Home-page: https://github.com/martinm07/tokenization-layer
Author: Martin Molnar
Author-email: martin.molnar07@gmail.com
License: UNKNOWN
Project-URL: Package Documentation, https://martin-github07.gitbook.io/tokenization-layer/
Project-URL: Bug Tracker, https://github.com/martinm07/tokenization-layer/issues
Project-URL: Project Discussion, https://github.com/martinm07/tokenization-layer/discussions
Keywords: natural-language-processing,research,neural-networks,tokenization,tensorflow2
Platform: UNKNOWN
Classifier: Programming Language :: Python :: 3.6
Classifier: License :: OSI Approved :: MIT License
Classifier: Operating System :: OS Independent
Requires-Python: >=3.6
License-File: LICENSE
Requires-Dist: tensorflow (>=2.0.0)
Requires-Dist: numpy (>=1.15.0)
Requires-Dist: pandas (>=1.0)
Requires-Dist: colorama
